remote_execute/__init__.py
remote_execute/remote_execute.py
remote_execute-1.6.dist-info/METADATA
remote_execute-1.6.dist-info/WHEEL
remote_execute-1.6.dist-info/entry_points.txt
remote_execute-1.6.dist-info/top_level.txt
remote_execute-1.6.dist-info/RECORD
