Metadata-Version: 2.1
Name: remote-execute
Version: 1.6
Summary: Execute remote code fetched from a URL
Home-page: https://github.com/ZynoSoftware/remote-execute
Author: WavaDev
License: UNKNOWN
Platform: UNKNOWN
Requires-Dist: requests
